verilog/brownout_dig.v
module brownout_dig(
//INPUTS
input logic [2:0] otrip,
input logic [2:0] vtrip,
input logic ena,
input logic force_rc_osc,
input logic force_short_oneshot,
input logic brout_filt,
input logic osc_ck,
//OUTPUTS
output osc_ena,
output out_unbuf,
output logic [7:0] otrip_decoded,
output logic [7:0] vtrip_decoded,
//DEBUG OUTPUTS
output logic osc_ck_256,
output timed_out
);

  //assign vunder = vunder_unbuf;

  //TRIP-VOLTAGE 3-to-8 DECODERS
  always @ (otrip) begin
    case(otrip)
      3'b111: otrip_decoded = 8'b10000000;
      3'b110: otrip_decoded = 8'b01000000;
      3'b101: otrip_decoded = 8'b00100000;
      3'b100: otrip_decoded = 8'b00010000;
      3'b011: otrip_decoded = 8'b00001000;
      3'b010: otrip_decoded = 8'b00000100;
      3'b001: otrip_decoded = 8'b00000010;
      3'b000: otrip_decoded = 8'b00000001;
    endcase
  end

  always @ (vtrip) begin
    case(vtrip)
      3'b111: vtrip_decoded = 8'b10000000;
      3'b110: vtrip_decoded = 8'b01000000;
      3'b101: vtrip_decoded = 8'b00100000;
      3'b100: vtrip_decoded = 8'b00010000;
      3'b011: vtrip_decoded = 8'b00001000;
      3'b010: vtrip_decoded = 8'b00000100;
      3'b001: vtrip_decoded = 8'b00000010;
      3'b000: vtrip_decoded = 8'b00000001;
    endcase
  end

  assign osc_ena = force_rc_osc | (ena & (brout_filt | !out_unbuf));
  wire brout_filt_ena_rsb;

  //BROUT_FILT RETIMER
  reg brout_filt_retime_rsb_stg1, brout_filt_retime_rsb;
  assign brout_filt_ena_rsb = ena & brout_filt;

  always @ (posedge osc_ck or negedge brout_filt_ena_rsb) begin
    if (!brout_filt_ena_rsb) begin
      brout_filt_retime_rsb_stg1 <= 0;
      brout_filt_retime_rsb <= 0;
    end else begin
      brout_filt_retime_rsb_stg1 <= 1;
      brout_filt_retime_rsb <= brout_filt_retime_rsb_stg1;
    end
  end

  reg brout_filt_retimed_stg1, brout_filt_retimed;
  always @ (posedge osc_ck or negedge brout_filt_retime_rsb) begin
    if (!brout_filt_retime_rsb) begin
      brout_filt_retimed_stg1 <= 0;
      brout_filt_retimed <= 0;
    end else begin
      brout_filt_retimed_stg1 <= brout_filt;
      brout_filt_retimed <= brout_filt_retimed_stg1;
    end
  end

  //COUNTER RESET
  reg cnt_rsb_stg1, cnt_rsb_stg2, cnt_rsb;

  always @ (posedge osc_ck or negedge ena) begin
    if (!ena) begin
      cnt_rsb_stg1 <= 0;
      cnt_rsb_stg2 <= 0;
      cnt_rsb <= 0;
    end else begin
      cnt_rsb_stg1 <= 1;
      cnt_rsb_stg2 <= cnt_rsb_stg1;
      cnt_rsb <= cnt_rsb_stg2;
    end
  end

  //16-BIT BROWN-OUT ONE-SHOT
  reg [15:0] cnt;

  assign timed_out = (cnt == 16'b1111111111111111);
  assign out_unbuf = brout_filt_retimed ? 0 : timed_out;

  always @ (posedge osc_ck or negedge cnt_rsb) begin
    if (!cnt_rsb) begin
      cnt <= 16'b1111111111111111;
    end else begin
      cnt <= brout_filt_retimed ? 0 : timed_out ? cnt : force_short_oneshot ? (cnt & 16'b1111000000000000) + 13'b1111111111111 : cnt + 1;
    end
  end

  //OUTPUT
  //DEBUG osc_ck/256
  reg [6:0] cnt_ck_256;

  always @ (posedge osc_ck or negedge brout_filt_retime_rsb) begin
    if (!brout_filt_retime_rsb) begin
      cnt_ck_256 <= 0;
      osc_ck_256 <= 0;
    end else begin
      cnt_ck_256 <= cnt_ck_256 + 1;
      osc_ck_256 <= (cnt_ck_256 == 7'b1111111) ? !osc_ck_256 : osc_ck_256;
    end
  end

endmodule

verilog/behavioral/rc_osc.v
################################################################################        
#Copyright 2024 Ajacci, Ltd. Co.
#License: Apache License, Version 2.0 with Addendum, see NOTICE
#Date: 22 March, 2024   Rev 0
#Description: RC oscillator model
################################################################################

module rc_osc(
input logic osc_ena,
input logic dvdd,
input logic dvss,
output logic osc_ck
);

always #12195.2 osc_ck = osc_ena ? ~osc_ck : 0;

initial begin
  osc_ck <= 0;
end
endmodule

verilog/behavioral/comparator.v
################################################################################        
#Copyright 2024 Ajacci, Ltd. Co.
#License: Apache License, Version 2.0 with Addendum, see NOTICE
#Date: 22 March, 2024   Rev 0
#Description: Comparator model
################################################################################

module comparator(
input real avdd,
input logic avss,
input logic dvdd,
input logic dvss,
input real vinp,
input real vinn,
input logic ena,
input real ibias,
output dout
);

assign dout = ena & (ibias > 200e-9) ? (vinp > vinn) ? 1 : 0 : 0;

endmodule

verilog/behavioral/ibias_gen.v
################################################################################        
#Copyright 2024 Ajacci, Ltd. Co.
#License: Apache License, Version 2.0 with Addendum, see NOTICE
#Date: 22 March, 2024   Rev 0
#Description: Bias generator model
################################################################################

module ibias_gen(
input real avdd,
input logic avss,
input logic dvdd,
input logic dvss,
input logic ena,
input logic isrc_sel,
input real ibg_200n,
output real ibias,
output real itest
);

assign ibias = ena ? isrc_sel ? 800e-9 : 700e-9 : 0;

endmodule

verilog/behavioral/rstring_mux.v
module rstring_mux(
//INPUT
input real avdd,
input logic avss,
input logic dvdd,
input logic dvss,
input logic ena,
input logic [7:0] otrip_decoded,
input logic [7:0] vtrip_decoded,
//OUTPUTS
output real vin_brout,
output real vin_vunder
);

`define UNIT_R 50e3

real vtrip_7;
real vtrip_6;
real vtrip_5;
real vtrip_4;
real vtrip_3;
real vtrip_2;
real vtrip_1;
real vtrip_0;

assign vtrip_0 = ena ? avdd * (`UNIT_R*7 + `UNIT_R*28) / (`UNIT_R*70) : avdd;
assign vtrip_1 = ena ? avdd * (`UNIT_R*6 + `UNIT_R*28) / (`UNIT_R*70) : avdd;
assign vtrip_2 = ena ? avdd * (`UNIT_R*5 + `UNIT_R*28) / (`UNIT_R*70) : avdd;
assign vtrip_3 = ena ? avdd * (`UNIT_R*4 + `UNIT_R*28) / (`UNIT_R*70) : avdd;
assign vtrip_4 = ena ? avdd * (`UNIT_R*3 + `UNIT_R*28) / (`UNIT_R*70) : avdd;
assign vtrip_5 = ena ? avdd * (`UNIT_R*2 + `UNIT_R*28) / (`UNIT_R*70) : avdd;
assign vtrip_6 = ena ? avdd * (`UNIT_R*1 + `UNIT_R*28) / (`UNIT_R*70) : avdd;
assign vtrip_7 = ena ? avdd * (`UNIT_R*0 + `UNIT_R*28) / (`UNIT_R*70) : avdd;

  always @ (vtrip_7, vtrip_6, vtrip_5, vtrip_4, vtrip_3, vtrip_2, vtrip_1, vtrip_0, otrip_decoded) begin
    case (otrip_decoded)
      8'b10000000: vin_brout = vtrip_7;
      8'b01000000: vin_brout = vtrip_6;
      8'b00100000: vin_brout = vtrip_5;
      8'b00010000: vin_brout = vtrip_4;
      8'b00001000: vin_brout = vtrip_3;
      8'b00000100: vin_brout = vtrip_2;
      8'b00000010: vin_brout = vtrip_1;
      8'b00000001: vin_brout = vtrip_0;
      default: vin_brout = 0;
    endcase
  end

  always @ (vtrip_7, vtrip_6, vtrip_5, vtrip_4, vtrip_3, vtrip_2, vtrip_1, vtrip_0, otrip_decoded) begin
    case (vtrip_decoded)
      8'b10000000: vin_vunder = vtrip_7;
      8'b01000000: vin_vunder = vtrip_6;
      8'b00100000: vin_vunder = vtrip_5;
      8'b00010000: vin_vunder = vtrip_4;
      8'b00001000: vin_vunder = vtrip_3;
      8'b00000100: vin_vunder = vtrip_2;
      8'b00000010: vin_vunder = vtrip_1;
      8'b00000001: vin_vunder = vtrip_0;
      default: vin_vunder = 0;
    endcase
  end

endmodule

verilog/brownout_ana.v
module brownout_ana(
//INPUTS
input real avdd,
input logic avss,
input logic dvdd,
input logic dvss,
input logic [7:0] otrip_decoded,
input logic [7:0] vtrip_decoded,
input real vbg_1v2,
input logic ena,
input logic isrc_sel,
input real ibg_200n,
input logic osc_ena,
input logic out_unbuf,
//OUTPTUS
output brout_filt,
output out,
output vunder,
output osc_ck,
output real vin_brout,
output real vin_vunder,
output real itest
);

//BUFFERS
assign vunder = ~vunder_unbuf;
assign out = out_unbuf;

rstring_mux rstring_mux(
.avdd(avdd),
.avss(avss),
.dvdd(dvdd),
.dvss(dvss),
.ena(ena),
.otrip_decoded(otrip_decoded), //lvls not modeled
.vtrip_decoded(vtrip_decoded), //lvls not modeled
.vin_brout(vin_brout),
.vin_vunder(vin_vunder)
);

real ibias;

ibias_gen ibias_gen(
.avdd(avdd),
.avss(avss),
.dvdd(dvdd),
.dvss(dvss),
.ena(ena),
.isrc_sel(isrc_sel),
.ibg_200n(ibg_200n),
.ibias(ibias),
.itest(itest)
);

comparator comparator_brout(
.avdd(avdd),
.avss(avss),
.dvdd(dvdd),
.dvss(dvss),
.vinp(vbg_1v2),
.vinn(vin_brout),
.ena(ena),
.ibias(ibias),
.dout(brout_filt)
);

comparator comparator_vunder(
.avdd(avdd),
.avss(avss),
.dvdd(dvdd),
.dvss(dvss),
.vinp(vbg_1v2),
.vinn(vin_vunder),
.ena(ena),
.ibias(ibias),
.dout(vunder_unbuf)
);

rc_osc rc_osc(
.dvdd(dvdd),
.dvss(dvss),
.osc_ena(osc_ena),
.osc_ck(osc_ck)
);

endmodule

verilog/brownout.v
`include "behavioral/rc_osc.v"
`include "behavioral/rstring_mux.v"
`include "behavioral/comparator.v"
`include "behavioral/ibias_gen.v"
`include "brownout_ana.v"
`include "brownout_dig.v"

module brownout(
//INPUTS
input real avdd,
input logic avss,
input logic dvdd,
input logic dvss,
input real vbg_1v2,
input logic [2:0] otrip,
input logic [2:0] vtrip,
input logic ena,
input logic force_rc_osc,
input logic force_short_oneshot,
input logic isrc_sel, //chooses between internal bias gen (0) or external bandgap current (1)
input real ibg_200n, //200nA bandgap current
//OUTPUTS
output out,
output vunder,
//DEBUG OUTPUTS
output osc_ck,
output osc_ck_256,
output real itest, //700nA bias current
output brout_filt,
output real vin_brout,
output real vin_vunder,
output timed_out
);

wire [7:0] otrip_decoded;
wire [7:0] vtrip_decoded;

brownout_ana brownout_ana(
//INPUTS
.avdd(avdd),
.avss(avss),
.dvdd(dvdd),
.dvss(dvss),
.otrip_decoded(otrip_decoded),
.vtrip_decoded(vtrip_decoded),
.vbg_1v2(vbg_1v2),
.ena(ena),
.isrc_sel(isrc_sel),
.ibg_200n(ibg_200n),
.osc_ena(osc_ena),
.out_unbuf(out_unbuf),
//OUTPUTS
.brout_filt(brout_filt),
.out(out),
.vunder(vunder),
.osc_ck(osc_ck),
//DEBUG OUTPUTS
.vin_brout(vin_brout), //input to comparator for comparing to 1.2V bg voltage
.vin_vunder(vin_vunder), //input to comparator for comparing to 1.2V bg voltage
.itest(itest) //mirror of current gen 0.7uA nominal
);

brownout_dig brownout_dig(
//INPUTS
.otrip(otrip),
.vtrip(vtrip),
.ena(ena),
.force_rc_osc(force_rc_osc),
.force_short_oneshot(force_short_oneshot),
.brout_filt(brout_filt),
//.vunder_unbuf(vunder_unbuf),
.osc_ck(osc_ck),
//OUTPUTS
.osc_ena(osc_ena),
.out_unbuf(out_unbuf),
//.vunder(vunder),
.otrip_decoded(otrip_decoded),
.vtrip_decoded(vtrip_decoded),
//DEBUG OUTPUTS
.osc_ck_256(osc_ck_256),
.timed_out(timed_out)
);

endmodule

verilog/tb_brownout.v
`include "brownout.v"
module tb_brownout();

real avdd;
real vbg_1v2;
logic [2:0] otrip;
logic [2:0] vtrip;
logic ena;
logic force_rc_osc;
logic force_short_oneshot;
logic isrc_sel;
real ibg_200n;
real vin_brout;
real vin_vunder;

brownout brownout(
//INPUTS
.avdd(avdd),
.avss(avss),
.dvdd(dvdd),
.dvss(dvss),
.vbg_1v2(vbg_1v2),
.otrip(otrip),
.vtrip(vtrip),
.ena(ena), //debug
.force_rc_osc(force_rc_osc), //debug
.force_short_oneshot(force_short_oneshot), //debug, fast sim
.isrc_sel(isrc_sel), //debug
.ibg_200n(ibg_200n), //debug 200nA current
//OUTPUTS
.out(out),
.vunder(vunder),
//DEBUG OUTPUTS
.osc_ck(osc_ck),
.osc_ck_256(osc_ck_256),
.itest(itest),
.brout_filt(brout_filt),
.vin_brout(vin_brout),
.vin_vunder(vin_vunder),
.timed_out(timed_out)
);

assign avss = 1'b0;
assign dvdd = 1'b1;
assign dvss = 1'b0;

initial begin
  $dumpfile("tb_brownout.vcd");
  $dumpvars(0,tb_brownout);

  //INPUTS
  avdd = 2.2;
  vbg_1v2 = 1.2;
  otrip = 3'b111;
  vtrip = 3'b111;
  //DEBUG INPUTS
  ena = 1'b0;
  force_rc_osc = 1'b0;
  force_short_oneshot = 1'b0;
  isrc_sel = 1'b0;
  ibg_200n = 200e-9;
  #8000000
  avdd = 3.3;
  #8000000
  ena = 1'b1;
  #8000000
  avdd = 2.2;
  #8000000
  avdd = 3.3;
  #120000000
  $finish;
end


endmodule

verilog/tb_brownout.vcd
$date
	Thu Mar 14 12:35:49 2024
$end
$version
	Icarus Verilog
$end
$timescale
	1s
$end
$scope module tb_brownout $end
$var wire 1 ! avss $end
$var wire 1 " dvdd $end
$var wire 1 # dvss $end
$var wire 1 $ vunder $end
$var wire 1 % timed_out $end
$var wire 1 & out $end
$var wire 1 ' osc_ck_256 $end
$var wire 1 ( osc_ck $end
$var wire 1 ) itest $end
$var wire 1 * brout_filt $end
$var reg 1 + ena $end
$var reg 1 , force_rc_osc $end
$var reg 1 - force_short_oneshot $end
$var reg 1 . isrc_sel $end
$var reg 3 / otrip [2:0] $end
$var reg 3 0 vtrip [2:0] $end
$var real 1 1 avdd $end
$var real 1 2 ibg_200n $end
$var real 1 3 vbg_1v2 $end
$var real 1 4 vin_vunder $end
$var real 1 5 vin_brout $end
$scope module brownout $end
$var wire 1 ! avss $end
$var wire 1 " dvdd $end
$var wire 1 # dvss $end
$var wire 1 + ena $end
$var wire 1 , force_rc_osc $end
$var wire 1 - force_short_oneshot $end
$var wire 1 . isrc_sel $end
$var wire 3 6 otrip [2:0] $end
$var wire 3 7 vtrip [2:0] $end
$var wire 1 $ vunder $end
$var wire 8 8 vtrip_decoded [7:0] $end
$var wire 1 % timed_out $end
$var wire 1 9 out_unbuf $end
$var wire 1 & out $end
$var wire 8 : otrip_decoded [7:0] $end
$var wire 1 ; osc_ena $end
$var wire 1 ' osc_ck_256 $end
$var wire 1 ( osc_ck $end
$var wire 1 * brout_filt $end
$var real 1 < avdd $end
$var real 1 = ibg_200n $end
$var real 1 > vbg_1v2 $end
$var real 1 ? vin_vunder $end
$var real 1 @ vin_brout $end
$var real 1 A itest $end
$scope module brownout_ana $end
$var wire 1 ! avss $end
$var wire 1 " dvdd $end
$var wire 1 # dvss $end
$var wire 1 + ena $end
$var wire 1 . isrc_sel $end
$var wire 1 & out $end
$var wire 1 $ vunder $end
$var wire 1 B vunder_unbuf $end
$var wire 8 C vtrip_decoded [7:0] $end
$var wire 1 9 out_unbuf $end
$var wire 8 D otrip_decoded [7:0] $end
$var wire 1 ; osc_ena $end
$var wire 1 ( osc_ck $end
$var wire 1 * brout_filt $end
$var real 1 E avdd $end
$var real 1 F ibg_200n $end
$var real 1 G vbg_1v2 $end
$var real 1 H vin_vunder $end
$var real 1 I vin_brout $end
$var real 1 J itest $end
$var real 1 K ibias $end
$scope module comparator_brout $end
$var wire 1 ! avss $end
$var wire 1 " dvdd $end
$var wire 1 # dvss $end
$var wire 1 + ena $end
$var wire 1 * dout $end
$var real 1 L avdd $end
$var real 1 M vinp $end
$var real 1 N vinn $end
$var real 1 O ibias $end
$upscope $end
$scope module comparator_vunder $end
$var wire 1 ! avss $end
$var wire 1 " dvdd $end
$var wire 1 # dvss $end
$var wire 1 + ena $end
$var wire 1 B dout $end
$var real 1 P avdd $end
$var real 1 Q vinp $end
$var real 1 R vinn $end
$var real 1 S ibias $end
$upscope $end
$scope module ibias_gen $end
$var wire 1 ! avss $end
$var wire 1 " dvdd $end
$var wire 1 # dvss $end
$var wire 1 + ena $end
$var wire 1 . isrc_sel $end
$var real 1 T avdd $end
$var real 1 U ibg_200n $end
$var real 1 V itest $end
$var real 1 W ibias $end
$upscope $end
$scope module rc_osc $end
$var wire 1 " dvdd $end
$var wire 1 # dvss $end
$var wire 1 ; osc_ena $end
$var reg 1 ( osc_ck $end
$upscope $end
$scope module rstring_mux $end
$var wire 1 ! avss $end
$var wire 1 " dvdd $end
$var wire 1 # dvss $end
$var wire 1 + ena $end
$var wire 8 X vtrip_decoded [7:0] $end
$var wire 8 Y otrip_decoded [7:0] $end
$var real 1 Z avdd $end
$var real 1 [ vin_brout $end
$var real 1 \ vin_vunder $end
$var real 1 ] vtrip_7 $end
$var real 1 ^ vtrip_6 $end
$var real 1 _ vtrip_5 $end
$var real 1 ` vtrip_4 $end
$var real 1 a vtrip_3 $end
$var real 1 b vtrip_2 $end
$var real 1 c vtrip_1 $end
$var real 1 d vtrip_0 $end
$upscope $end
$upscope $end
$scope module brownout_dig $end
$var wire 1 * brout_filt $end
$var wire 1 e brout_filt_ena_rsb $end
$var wire 1 + ena $end
$var wire 1 , force_rc_osc $end
$var wire 1 - force_short_oneshot $end
$var wire 1 ( osc_ck $end
$var wire 1 ; osc_ena $end
$var wire 3 f otrip [2:0] $end
$var wire 3 g vtrip [2:0] $end
$var wire 1 % timed_out $end
$var wire 1 9 out_unbuf $end
$var reg 1 h brout_filt_retime_rsb $end
$var reg 1 i brout_filt_retime_rsb_stg1 $end
$var reg 1 j brout_filt_retimed $end
$var reg 1 k brout_filt_retimed_stg1 $end
$var reg 16 l cnt [15:0] $end
$var reg 7 m cnt_ck_256 [6:0] $end
$var reg 1 n cnt_rsb $end
$var reg 1 o cnt_rsb_stg1 $end
$var reg 1 p cnt_rsb_stg2 $end
$var reg 1 ' osc_ck_256 $end
$var reg 8 q otrip_decoded [7:0] $end
$var reg 8 r vtrip_decoded [7:0] $end
$upscope $end
$upscope $end
$upscope $end
$enddefinitions $end
$comment Show the parameter values. $end
$dumpall
$end
#0
$dumpvars
b10000000 r
b10000000 q
0p
0o
0n
b0 m
b1111111111111111 l
0k
0j
0i
0h
b111 g
b111 f
0e
r2.2 d
r2.2 c
r2.2 b
r2.2 a
r2.2 `
r2.2 _
r2.2 ^
r2.2 ]
r2.2 \
r2.2 [
r2.2 Z
b10000000 Y
b10000000 X
r0 W
r0 V
r2e-07 U
r2.2 T
r0 S
r2.2 R
r1.2 Q
r2.2 P
r0 O
r2.2 N
r1.2 M
r2.2 L
r0 K
r0 J
r2.2 I
r2.2 H
r1.2 G
r2e-07 F
r2.2 E
b10000000 D
b10000000 C
0B
r0 A
r2.2 @
r2.2 ?
r1.2 >
r2e-07 =
r2.2 <
0;
b10000000 :
19
b10000000 8
b111 7
b111 6
r2.2 5
r2.2 4
r1.2 3
r2e-07 2
r2.2 1
b111 0
b111 /
0.
0-
0,
0+
0*
0)
0(
0'
1&
1%
0$
0#
1"
0!
$end
#8000000
r3.3 5
r3.3 @
r3.3 I
r3.3 N
r3.3 [
r3.3 4
r3.3 ?
r3.3 H
r3.3 R
r3.3 \
r3.3 d
r3.3 c
r3.3 b
r3.3 a
r3.3 `
r3.3 _
r3.3 ^
r3.3 ]
r3.3 1
r3.3 <
r3.3 E
r3.3 L
r3.3 P
r3.3 T
r3.3 Z
#16000000
r1.32 4
r1.32 ?
r1.32 H
r1.32 R
r1.32 \
r1.32 5
r1.32 @
r1.32 I
r1.32 N
r1.32 [
r7e-07 K
r7e-07 O
r7e-07 S
r7e-07 W
r1.65 d
r1.602857142857143 c
r1.555714285714286 b
r1.508571428571429 a
r1.461428571428572 `
r1.414285714285714 _
r1.367142857142857 ^
r1.32 ]
1+
#24000000
1;
1e
1*
1$
1B
r0.8800000000000001 5
r0.8800000000000001 @
r0.8800000000000001 I
r0.8800000000000001 N
r0.8800000000000001 [
r0.8800000000000001 4
r0.8800000000000001 ?
r0.8800000000000001 H
r0.8800000000000001 R
r0.8800000000000001 \
r1.1 d
r1.068571428571429 c
r1.037142857142857 b
r1.005714285714286 a
r0.9742857142857144 `
r0.9428571428571429 _
r0.9114285714285716 ^
r0.8800000000000001 ]
r2.2 1
r2.2 <
r2.2 E
r2.2 L
r2.2 P
r2.2 T
r2.2 Z
#24000714
1o
1i
1(
#24001476
0(
#24002238
1p
1h
1(
#24003000
0(
#24003762
b1 m
1k
1n
1(
#24004524
0(
#24005286
0&
09
1j
b10 m
1(
#24006048
0(
#24006810
b11 m
0%
b0 l
1(
#24007572
0(
#24008334
b100 m
1(
#24009096
0(
#24009858
b101 m
1(
#24010620
0(
#24011382
b110 m
1(
#24012144
0(
#24012906
b111 m
1(
#24013668
0(
#24014430
b1000 m
1(
#24015192
0(
#24015954
b1001 m
1(
#24016716
0(
#24017478
b1010 m
1(
#24018240
0(
#24019002
b1011 m
1(
#24019764
0(
#24020526
b1100 m
1(
#24021288
0(
#24022050
b1101 m
1(
#24022812
0(
#24023574
b1110 m
1(
#24024336
0(
#24025098
b1111 m
1(
#24025860
0(
#24026622
b10000 m
1(
#24027384
0(
#24028146
b10001 m
1(
#24028908
0(
#24029670
b10010 m
1(
#24030432
0(
#24031194
b10011 m
1(
#24031956
0(
#24032718
b10100 m
1(
#24033480
0(
#24034242
b10101 m
1(
#24035004
0(
#24035766
b10110 m
1(
#24036528
0(
#24037290
b10111 m
1(
#24038052
0(
#24038814
b11000 m
1(
#24039576
0(
#24040338
b11001 m
1(
#24041100
0(
#24041862
b11010 m
1(
#24042624
0(
#24043386
b11011 m
1(
#24044148
0(
#24044910
b11100 m
1(
#24045672
0(
#24046434
b11101 m
1(
#24047196
0(
#24047958
b11110 m
1(
#24048720
0(
#24049482
b11111 m
1(
#24050244
0(
#24051006
b100000 m
1(
#24051768
0(
#24052530
b100001 m
1(
#24053292
0(
#24054054
b100010 m
1(
#24054816
0(
#24055578
b100011 m
1(
#24056340
0(
#24057102
b100100 m
1(
#24057864
0(
#24058626
b100101 m
1(
#24059388
0(
#24060150
b100110 m
1(
#24060912
0(
#24061674
b100111 m
1(
#24062436
0(
#24063198
b101000 m
1(
#24063960
0(
#24064722
b101001 m
1(
#24065484
0(
#24066246
b101010 m
1(
#24067008
0(
#24067770
b101011 m
1(
#24068532
0(
#24069294
b101100 m
1(
#24070056
0(
#24070818
b101101 m
1(
#24071580
0(
#24072342
b101110 m
1(
#24073104
0(
#24073866
b101111 m
1(
#24074628
0(
#24075390
b110000 m
1(
#24076152
0(
#24076914
b110001 m
1(
#24077676
0(
#24078438
b110010 m
1(
#24079200
0(
#24079962
b110011 m
1(
#24080724
0(
#24081486
b110100 m
1(
#24082248
0(
#24083010
b110101 m
1(
#24083772
0(
#24084534
b110110 m
1(
#24085296
0(
#24086058
b110111 m
1(
#24086820
0(
#24087582
b111000 m
1(
#24088344
0(
#24089106
b111001 m
1(
#24089868
0(
#24090630
b111010 m
1(
#24091392
0(
#24092154
b111011 m
1(
#24092916
0(
#24093678
b111100 m
1(
#24094440
0(
#24095202
b111101 m
1(
#24095964
0(
#24096726
b111110 m
1(
#24097488
0(
#24098250
b111111 m
1(
#24099012
0(
#24099774
b1000000 m
1(
#24100536
0(
#24101298
b1000001 m
1(
#24102060
0(
#24102822
b1000010 m
1(
#24103584
0(
#24104346
b1000011 m
1(
#24105108
0(
#24105870
b1000100 m
1(
#24106632
0(
#24107394
b1000101 m
1(
#24108156
0(
#24108918
b1000110 m
1(
#24109680
0(
#24110442
b1000111 m
1(
#24111204
0(
#24111966
b1001000 m
1(
#24112728
0(
#24113490
b1001001 m
1(
#24114252
0(
#24115014
b1001010 m
1(
#24115776
0(
#24116538
b1001011 m
1(
#24117300
0(
#24118062
b1001100 m
1(
#24118824
0(
#24119586
b1001101 m
1(
#24120348
0(
#24121110
b1001110 m
1(
#24121872
0(
#24122634
b1001111 m
1(
#24123396
0(
#24124158
b1010000 m
1(
#24124920
0(
#24125682
b1010001 m
1(
#24126444
0(
#24127206
b1010010 m
1(
#24127968
0(
#24128730
b1010011 m
1(
#24129492
0(
#24130254
b1010100 m
1(
#24131016
0(
#24131778
b1010101 m
1(
#24132540
0(
#24133302
b1010110 m
1(
#24134064
0(
#24134826
b1010111 m
1(
#24135588
0(
#24136350
b1011000 m
1(
#24137112
0(
#24137874
b1011001 m
1(
#24138636
0(
#24139398
b1011010 m
1(
#24140160
0(
#24140922
b1011011 m
1(
#24141684
0(
#24142446
b1011100 m
1(
#24143208
0(
#24143970
b1011101 m
1(
#24144732
0(
#24145494
b1011110 m
1(
#24146256
0(
#24147018
b1011111 m
1(
#24147780
0(
#24148542
b1100000 m
1(
#24149304
0(
#24150066
b1100001 m
1(
#24150828
0(
#24151590
b1100010 m
1(
#24152352
0(
#24153114
b1100011 m
1(
#24153876
0(
#24154638
b1100100 m
1(
#24155400
0(
#24156162
b1100101 m
1(
#24156924
0(
#24157686
b1100110 m
1(
#24158448
0(
#24159210
b1100111 m
1(
#24159972
0(
#24160734
b1101000 m
1(
#24161496
0(
#24162258
b1101001 m
1(
#24163020
0(
#24163782
b1101010 m
1(
#24164544
0(
#24165306
b1101011 m
1(
#24166068
0(
#24166830
b1101100 m
1(
#24167592
0(
#24168354
b1101101 m
1(
#24169116
0(
#24169878
b1101110 m
1(
#24170640
0(
#24171402
b1101111 m
1(
#24172164
0(
#24172926
b1110000 m
1(
#24173688
0(
#24174450
b1110001 m
1(
#24175212
0(
#24175974
b1110010 m
1(
#24176736
0(
#24177498
b1110011 m
1(
#24178260
0(
#24179022
b1110100 m
1(
#24179784
0(
#24180546
b1110101 m
1(
#24181308
0(
#24182070
b1110110 m
1(
#24182832
0(
#24183594
b1110111 m
1(
#24184356
0(
#24185118
b1111000 m
1(
#24185880
0(
#24186642
b1111001 m
1(
#24187404
0(
#24188166
b1111010 m
1(
#24188928
0(
#24189690
b1111011 m
1(
#24190452
0(
#24191214
b1111100 m
1(
#24191976
0(
#24192738
b1111101 m
1(
#24193500
0(
#24194262
b1111110 m
1(
#24195024
0(
#24195786
b1111111 m
1(
#24196548
0(
#24197310
1'
b0 m
1(
#24198072
0(
#24198834
b1 m
1(
#24199596
0(
#24200358
b10 m
1(
#24201120
0(
#24201882
b11 m
1(
#24202644
0(
#24203406
b100 m
1(
#24204168
0(
#24204930
b101 m
1(
#24205692
0(
#24206454
b110 m
1(
#24207216
0(
#24207978
b111 m
1(
#24208740
0(
#24209502
b1000 m
1(
#24210264
0(
#24211026
b1001 m
1(
#24211788
0(
#24212550
b1010 m
1(
#24213312
0(
#24214074
b1011 m
1(
#24214836
0(
#24215598
b1100 m
1(
#24216360
0(
#24217122
b1101 m
1(
#24217884
0(
#24218646
b1110 m
1(
#24219408
0(
#24220170
b1111 m
1(
#24220932
0(
#24221694
b10000 m
1(
#24222456
0(
#24223218
b10001 m
1(
#24223980
0(
#24224742
b10010 m
1(
#24225504
0(
#24226266
b10011 m
1(
#24227028
0(
#24227790
b10100 m
1(
#24228552
0(
#24229314
b10101 m
1(
#24230076
0(
#24230838
b10110 m
1(
#24231600
0(
#24232362
b10111 m
1(
#24233124
0(
#24233886
b11000 m
1(
#24234648
0(
#24235410
b11001 m
1(
#24236172
0(
#24236934
b11010 m
1(
#24237696
0(
#24238458
b11011 m
1(
#24239220
0(
#24239982
b11100 m
1(
#24240744
0(
#24241506
b11101 m
1(
#24242268
0(
#24243030
b11110 m
1(
#24243792
0(
#24244554
b11111 m
1(
#24245316
0(
#24246078
b100000 m
1(
#24246840
0(
#24247602
b100001 m
1(
#24248364
0(
#24249126
b100010 m
1(
#24249888
0(
#24250650
b100011 m
1(
#24251412
0(
#24252174
b100100 m
1(
#24252936
0(
#24253698
b100101 m
1(
#24254460
0(
#24255222
b100110 m
1(
#24255984
0(
#24256746
b100111 m
1(
#24257508
0(
#24258270
b101000 m
1(
#24259032
0(
#24259794
b101001 m
1(
#24260556
0(
#24261318
b101010 m
1(
#24262080
0(
#24262842
b101011 m
1(
#24263604
0(
#24264366
b101100 m
1(
#24265128
0(
#24265890
b101101 m
1(
#24266652
0(
#24267414
b101110 m
1(
#24268176
0(
#24268938
b101111 m
1(
#24269700
0(
#24270462
b110000 m
1(
#24271224
0(
#24271986
b110001 m
1(
#24272748
0(
#24273510
b110010 m
1(
#24274272
0(
#24275034
b110011 m
1(
#24275796
0(
#24276558
b110100 m
1(
#24277320
0(
#24278082
b110101 m
1(
#24278844
0(
#24279606
b110110 m
1(
#24280368
0(
#24281130
b110111 m
1(
#24281892
0(
#24282654
b111000 m
1(
#24283416
0(
#24284178
b111001 m
1(
#24284940
0(
#24285702
b111010 m
1(
#24286464
0(
#24287226
b111011 m
1(
#24287988
0(
#24288750
b111100 m
1(
#24289512
0(
#24290274
b111101 m
1(
#24291036
0(
#24291798
b111110 m
1(
#24292560
0(
#24293322
b111111 m
1(
#24294084
0(
#24294846
b1000000 m
1(
#24295608
0(
#24296370
b1000001 m
1(
#24297132
0(
#24297894
b1000010 m
1(
#24298656
0(
#24299418
b1000011 m
1(
#24300180
0(
#24300942
b1000100 m
1(
#24301704
0(
#24302466
b1000101 m
1(
#24303228
0(
#24303990
b1000110 m
1(
#24304752
0(
#24305514
b1000111 m
1(
#24306276
0(
#24307038
b1001000 m
1(
#24307800
0(
#24308562
b1001001 m
1(
#24309324
0(
#24310086
b1001010 m
1(
#24310848
0(
#24311610
b1001011 m
1(
#24312372
0(
#24313134
b1001100 m
1(
#24313896
0(
#24314658
b1001101 m
1(
#24315420
0(
#24316182
b1001110 m
1(
#24316944
0(
#24317706
b1001111 m
1(
#24318468
0(
#24319230
b1010000 m
1(
#24319992
0(
#24320754
b1010001 m
1(
#24321516
0(
#24322278
b1010010 m
1(
#24323040
0(
#24323802
b1010011 m
1(
#24324564
0(
#24325326
b1010100 m
1(
#24326088
0(
#24326850
b1010101 m
1(
#24327612
0(
#24328374
b1010110 m
1(
#24329136
0(
#24329898
b1010111 m
1(
#24330660
0(
#24331422
b1011000 m
1(
