verilog/brownout_dig.v
module brownout_dig(
//INPUTS
input logic [2:0] otrip,
input logic [2:0] vtrip,
input logic ena,
input logic force_rc_osc,
input logic force_short_oneshot,
input logic brout_filt,
input logic osc_ck,
//OUTPUTS
output osc_ena,
output out_unbuf,
output logic [7:0] otrip_decoded,
output logic [7:0] vtrip_decoded,
//DEBUG OUTPUTS
output timed_out
);

  //assign vunder = vunder_unbuf;

  //TRIP-VOLTAGE 3-to-8 DECODERS
  always @ (otrip) begin
    case(otrip)
      3'b111: otrip_decoded = 8'b10000000;
      3'b110: otrip_decoded = 8'b01000000;
      3'b101: otrip_decoded = 8'b00100000;
      3'b100: otrip_decoded = 8'b00010000;
      3'b011: otrip_decoded = 8'b00001000;
      3'b010: otrip_decoded = 8'b00000100;
      3'b001: otrip_decoded = 8'b00000010;
      3'b000: otrip_decoded = 8'b00000001;
    endcase
  end

  always @ (vtrip) begin
    case(vtrip)
      3'b111: vtrip_decoded = 8'b10000000;
      3'b110: vtrip_decoded = 8'b01000000;
      3'b101: vtrip_decoded = 8'b00100000;
      3'b100: vtrip_decoded = 8'b00010000;
      3'b011: vtrip_decoded = 8'b00001000;
      3'b010: vtrip_decoded = 8'b00000100;
      3'b001: vtrip_decoded = 8'b00000010;
      3'b000: vtrip_decoded = 8'b00000001;
    endcase
  end

  assign osc_ena = force_rc_osc | (ena & (brout_filt | !out_unbuf));
  wire brout_filt_ena_rsb;

  //BROUT_FILT RETIME
  assign brout_filt_ena_rsb = ena & brout_filt;

  reg brout_filt_retimed;
  always @ (posedge osc_ck or negedge brout_filt_ena_rsb) begin
    if (!brout_filt_ena_rsb) begin
      brout_filt_retimed <= 0;
    end else begin
      brout_filt_retimed <= brout_filt;
    end
  end

  //COUNTER RESET
  reg cnt_rsb_stg1, cnt_rsb_stg2, cnt_rsb;

  always @ (posedge osc_ck or negedge ena) begin
    if (!ena) begin
      cnt_rsb_stg1 <= 0;
      cnt_rsb_stg2 <= 0;
      cnt_rsb <= 0;
    end else begin
      cnt_rsb_stg1 <= 1;
      cnt_rsb_stg2 <= cnt_rsb_stg1;
      cnt_rsb <= cnt_rsb_stg2;
    end
  end

  //12-BIT BROWN-OUT ONE-SHOT
  reg [11:0] cnt;

  assign timed_out = (cnt == 12'b111111111111);
  assign out_unbuf = brout_filt_retimed ? 0 : timed_out;

  always @ (posedge osc_ck or negedge cnt_rsb) begin
    if (!cnt_rsb) begin
      cnt <= 12'b111111111111;
    end else begin
      cnt <= brout_filt_retimed ? 0 : timed_out ? cnt : force_short_oneshot ? (cnt & 12'b111111000000) + 12'b000001111111 : cnt + 1;
    end
  end

endmodule

verilog/behavioral/rc_osc.v
################################################################################        
#Copyright 2024 Ajacci, Ltd. Co.
#License: Apache License, Version 2.0 with Addendum, see NOTICE
#Date: 22 March, 2024   Rev 0
#Description: RC oscillator model
################################################################################

module rc_osc(
input logic osc_ena,
input logic dvdd,
input logic dvss,
output logic osc_ck
);

always #12195.2 osc_ck = osc_ena ? ~osc_ck : 0;

initial begin
  osc_ck <= 0;
end
endmodule

verilog/behavioral/comparator.v
################################################################################        
#Copyright 2024 Ajacci, Ltd. Co.
#License: Apache License, Version 2.0 with Addendum, see NOTICE
#Date: 22 March, 2024   Rev 0
#Description: Comparator model
################################################################################

module comparator(
input real avdd,
input logic avss,
input logic dvdd,
input logic dvss,
input real vinp,
input real vinn,
input logic ena,
input real ibias,
output dout
);

assign dout = ena & (ibias > 200e-9) ? (vinp > vinn) ? 1 : 0 : 0;

endmodule

verilog/behavioral/ibias_gen.v
################################################################################        
#Copyright 2024 Ajacci, Ltd. Co.
#License: Apache License, Version 2.0 with Addendum, see NOTICE
#Date: 22 March, 2024   Rev 0
#Description: Bias generator model
################################################################################

module ibias_gen(
input real avdd,
input logic avss,
input logic dvdd,
input logic dvss,
input logic ena,
input logic isrc_sel,
input real ibg_200n,
output real ibias,
output real itest
);

assign ibias = ena ? isrc_sel ? 800e-9 : 700e-9 : 0;

endmodule

verilog/behavioral/rstring_mux.v
################################################################################        
#Copyright 2024 Ajacci, Ltd. Co.
#License: Apache License, Version 2.0 with Addendum, see NOTICE
#Date: 22 March, 2024   Rev 0
#Description: Resistor string with analog mux model
################################################################################

module rstring_mux(
//INPUT
input real avdd,
input logic avss,
input logic dvdd,
input logic dvss,
input logic ena,
input logic [7:0] otrip_decoded,
input logic [7:0] vtrip_decoded,
//OUTPUTS
output real vin_brout,
output real vin_vunder
);

`define UNIT_R 50e3

real vtrip_7;
real vtrip_6;
real vtrip_5;
real vtrip_4;
real vtrip_3;
real vtrip_2;
real vtrip_1;
real vtrip_0;

assign vtrip_0 = ena ? avdd * (`UNIT_R*7 + `UNIT_R*28) / (`UNIT_R*70) : avdd;
assign vtrip_1 = ena ? avdd * (`UNIT_R*6 + `UNIT_R*28) / (`UNIT_R*70) : avdd;
assign vtrip_2 = ena ? avdd * (`UNIT_R*5 + `UNIT_R*28) / (`UNIT_R*70) : avdd;
assign vtrip_3 = ena ? avdd * (`UNIT_R*4 + `UNIT_R*28) / (`UNIT_R*70) : avdd;
assign vtrip_4 = ena ? avdd * (`UNIT_R*3 + `UNIT_R*28) / (`UNIT_R*70) : avdd;
assign vtrip_5 = ena ? avdd * (`UNIT_R*2 + `UNIT_R*28) / (`UNIT_R*70) : avdd;
assign vtrip_6 = ena ? avdd * (`UNIT_R*1 + `UNIT_R*28) / (`UNIT_R*70) : avdd;
assign vtrip_7 = ena ? avdd * (`UNIT_R*0 + `UNIT_R*28) / (`UNIT_R*70) : avdd;

  always @ (vtrip_7, vtrip_6, vtrip_5, vtrip_4, vtrip_3, vtrip_2, vtrip_1, vtrip_0, otrip_decoded) begin
    case (otrip_decoded)
      8'b10000000: vin_brout = vtrip_7;
      8'b01000000: vin_brout = vtrip_6;
      8'b00100000: vin_brout = vtrip_5;
      8'b00010000: vin_brout = vtrip_4;
      8'b00001000: vin_brout = vtrip_3;
      8'b00000100: vin_brout = vtrip_2;
      8'b00000010: vin_brout = vtrip_1;
      8'b00000001: vin_brout = vtrip_0;
      default: vin_brout = 0;
    endcase
  end

  always @ (vtrip_7, vtrip_6, vtrip_5, vtrip_4, vtrip_3, vtrip_2, vtrip_1, vtrip_0, otrip_decoded) begin
    case (vtrip_decoded)
      8'b10000000: vin_vunder = vtrip_7;
      8'b01000000: vin_vunder = vtrip_6;
      8'b00100000: vin_vunder = vtrip_5;
      8'b00010000: vin_vunder = vtrip_4;
      8'b00001000: vin_vunder = vtrip_3;
      8'b00000100: vin_vunder = vtrip_2;
      8'b00000010: vin_vunder = vtrip_1;
      8'b00000001: vin_vunder = vtrip_0;
      default: vin_vunder = 0;
    endcase
  end

endmodule

verilog/brownout_ana.v
module brownout_ana(
//INPUTS
input real avdd,
input logic avss,
input logic dvdd,
input logic dvss,
input logic [7:0] otrip_decoded,
input logic [7:0] vtrip_decoded,
input real vbg_1v2,
input logic ena,
input logic isrc_sel,
input real ibg_200n,
input logic osc_ena,
input logic out_unbuf,
//OUTPTUS
output brout_filt,
output out,
output vunder,
output osc_ck,
output real vin_brout,
output real vin_vunder,
output real itest
);

//BUFFERS
assign vunder = ~vunder_unbuf;
assign out = out_unbuf;

rstring_mux rstring_mux(
.avdd(avdd),
.avss(avss),
.dvdd(dvdd),
.dvss(dvss),
.ena(ena),
.otrip_decoded(otrip_decoded), //lvls not modeled
.vtrip_decoded(vtrip_decoded), //lvls not modeled
.vin_brout(vin_brout),
.vin_vunder(vin_vunder)
);

real ibias;

ibias_gen ibias_gen(
.avdd(avdd),
.avss(avss),
.dvdd(dvdd),
.dvss(dvss),
.ena(ena),
.isrc_sel(isrc_sel),
.ibg_200n(ibg_200n),
.ibias(ibias),
.itest(itest)
);

comparator comparator_brout(
.avdd(avdd),
.avss(avss),
.dvdd(dvdd),
.dvss(dvss),
.vinp(vbg_1v2),
.vinn(vin_brout),
.ena(ena),
.ibias(ibias),
.dout(brout_filt)
);

comparator comparator_vunder(
.avdd(avdd),
.avss(avss),
.dvdd(dvdd),
.dvss(dvss),
.vinp(vbg_1v2),
.vinn(vin_vunder),
.ena(ena),
.ibias(ibias),
.dout(vunder_unbuf)
);

rc_osc rc_osc(
.dvdd(dvdd),
.dvss(dvss),
.osc_ena(osc_ena),
.osc_ck(osc_ck)
);

endmodule

verilog/brownout.v
`include "behavioral/rc_osc.v"
`include "behavioral/rstring_mux.v"
`include "behavioral/comparator.v"
`include "behavioral/ibias_gen.v"
`include "brownout_ana.v"
`include "brownout_dig.v"

module brownout(
//INPUTS
input real avdd,
input logic avss,
input logic dvdd,
input logic dvss,
input real vbg_1v2,
input logic [2:0] otrip,
input logic [2:0] vtrip,
input logic ena,
input logic force_rc_osc,
input logic force_short_oneshot,
input logic isrc_sel, //chooses between internal bias gen (0) or external bandgap current (1)
input real ibg_200n, //200nA bandgap current
//OUTPUTS
output out,
output vunder,
//DEBUG OUTPUTS
output osc_ck,
output real itest, //700nA bias current
output brout_filt,
output real vin_brout,
output real vin_vunder,
output timed_out
);

wire [7:0] otrip_decoded;
wire [7:0] vtrip_decoded;

brownout_ana brownout_ana(
//INPUTS
.avdd(avdd),
.avss(avss),
.dvdd(dvdd),
.dvss(dvss),
.otrip_decoded(otrip_decoded),
.vtrip_decoded(vtrip_decoded),
.vbg_1v2(vbg_1v2),
.ena(ena),
.isrc_sel(isrc_sel),
.ibg_200n(ibg_200n),
.osc_ena(osc_ena),
.out_unbuf(out_unbuf),
//OUTPUTS
.brout_filt(brout_filt),
.out(out),
.vunder(vunder),
.osc_ck(osc_ck),
//DEBUG OUTPUTS
.vin_brout(vin_brout), //input to comparator for comparing to 1.2V bg voltage
.vin_vunder(vin_vunder), //input to comparator for comparing to 1.2V bg voltage
.itest(itest) //mirror of current gen 0.7uA nominal
);

brownout_dig brownout_dig(
//INPUTS
.otrip(otrip),
.vtrip(vtrip),
.ena(ena),
.force_rc_osc(force_rc_osc),
.force_short_oneshot(force_short_oneshot),
.brout_filt(brout_filt),
//.vunder_unbuf(vunder_unbuf),
.osc_ck(osc_ck),
//OUTPUTS
.osc_ena(osc_ena),
.out_unbuf(out_unbuf),
//.vunder(vunder),
.otrip_decoded(otrip_decoded),
.vtrip_decoded(vtrip_decoded),
//DEBUG OUTPUTS
.timed_out(timed_out)
);

endmodule

verilog/tb_brownout.v
`include "brownout.v"
module tb_brownout();

real avdd;
real vbg_1v2;
logic [2:0] otrip;
logic [2:0] vtrip;
logic ena;
logic force_rc_osc;
logic force_short_oneshot;
logic isrc_sel;
real ibg_200n;
real vin_brout;
real vin_vunder;

brownout brownout(
//INPUTS
.avdd(avdd),
.avss(avss),
.dvdd(dvdd),
.dvss(dvss),
.vbg_1v2(vbg_1v2),
.otrip(otrip),
.vtrip(vtrip),
.ena(ena), //debug
.force_rc_osc(force_rc_osc), //debug
.force_short_oneshot(force_short_oneshot), //debug, fast sim
.isrc_sel(isrc_sel), //debug
.ibg_200n(ibg_200n), //debug 200nA current
//OUTPUTS
.out(out),
.vunder(vunder),
//DEBUG OUTPUTS
.osc_ck(osc_ck),
.itest(itest),
.brout_filt(brout_filt),
.vin_brout(vin_brout),
.vin_vunder(vin_vunder),
.timed_out(timed_out)
);

assign avss = 1'b0;
assign dvdd = 1'b1;
assign dvss = 1'b0;

initial begin
  $dumpfile("tb_brownout.vcd");
  $dumpvars(0,tb_brownout);

  //INPUTS
  avdd = 2.2;
  vbg_1v2 = 1.2;
  otrip = 3'b111;
  vtrip = 3'b111;
  //DEBUG INPUTS
  ena = 1'b0;
  force_rc_osc = 1'b0;
  force_short_oneshot = 1'b0;
  isrc_sel = 1'b0;
  ibg_200n = 200e-9;
  #8000000
  avdd = 3.3;
  #8000000
  ena = 1'b1;
  #8000000
  avdd = 2.2;
  #8000000
  avdd = 3.3;
  #120000000
  $finish;
end


endmodule

verilog/tb_brownout.vcd
$date
	Sun Mar 17 22:26:31 2024
$end
$version
	Icarus Verilog
$end
$timescale
	1s
$end
$scope module tb_brownout $end
$var wire 1 ! avss $end
$var wire 1 " dvdd $end
$var wire 1 # dvss $end
$var wire 1 $ vunder $end
$var wire 1 % timed_out $end
$var wire 1 & out $end
$var wire 1 ' osc_ck $end
$var wire 1 ( itest $end
$var wire 1 ) brout_filt $end
$var reg 1 * ena $end
$var reg 1 + force_rc_osc $end
$var reg 1 , force_short_oneshot $end
$var reg 1 - isrc_sel $end
$var reg 3 . otrip [2:0] $end
$var reg 3 / vtrip [2:0] $end
$var real 1 0 avdd $end
$var real 1 1 ibg_200n $end
$var real 1 2 vbg_1v2 $end
$var real 1 3 vin_vunder $end
$var real 1 4 vin_brout $end
$scope module brownout $end
$var wire 1 ! avss $end
$var wire 1 " dvdd $end
$var wire 1 # dvss $end
$var wire 1 * ena $end
$var wire 1 + force_rc_osc $end
$var wire 1 , force_short_oneshot $end
$var wire 1 - isrc_sel $end
$var wire 3 5 otrip [2:0] $end
$var wire 3 6 vtrip [2:0] $end
$var wire 1 $ vunder $end
$var wire 8 7 vtrip_decoded [7:0] $end
$var wire 1 % timed_out $end
$var wire 1 8 out_unbuf $end
$var wire 1 & out $end
$var wire 8 9 otrip_decoded [7:0] $end
$var wire 1 : osc_ena $end
$var wire 1 ' osc_ck $end
$var wire 1 ) brout_filt $end
$var real 1 ; avdd $end
$var real 1 < ibg_200n $end
$var real 1 = vbg_1v2 $end
$var real 1 > vin_vunder $end
$var real 1 ? vin_brout $end
$var real 1 @ itest $end
$scope module brownout_ana $end
$var wire 1 ! avss $end
$var wire 1 " dvdd $end
$var wire 1 # dvss $end
$var wire 1 * ena $end
$var wire 1 - isrc_sel $end
$var wire 1 & out $end
$var wire 1 $ vunder $end
$var wire 1 A vunder_unbuf $end
$var wire 8 B vtrip_decoded [7:0] $end
$var wire 1 8 out_unbuf $end
$var wire 8 C otrip_decoded [7:0] $end
$var wire 1 : osc_ena $end
$var wire 1 ' osc_ck $end
$var wire 1 ) brout_filt $end
$var real 1 D avdd $end
$var real 1 E ibg_200n $end
$var real 1 F vbg_1v2 $end
$var real 1 G vin_vunder $end
$var real 1 H vin_brout $end
$var real 1 I itest $end
$var real 1 J ibias $end
$scope module comparator_brout $end
$var wire 1 ! avss $end
$var wire 1 " dvdd $end
$var wire 1 # dvss $end
$var wire 1 * ena $end
$var wire 1 ) dout $end
$var real 1 K avdd $end
$var real 1 L vinp $end
$var real 1 M vinn $end
$var real 1 N ibias $end
$upscope $end
$scope module comparator_vunder $end
$var wire 1 ! avss $end
$var wire 1 " dvdd $end
$var wire 1 # dvss $end
$var wire 1 * ena $end
$var wire 1 A dout $end
$var real 1 O avdd $end
$var real 1 P vinp $end
$var real 1 Q vinn $end
$var real 1 R ibias $end
$upscope $end
$scope module ibias_gen $end
$var wire 1 ! avss $end
$var wire 1 " dvdd $end
$var wire 1 # dvss $end
$var wire 1 * ena $end
$var wire 1 - isrc_sel $end
$var real 1 S avdd $end
$var real 1 T ibg_200n $end
$var real 1 U itest $end
$var real 1 V ibias $end
$upscope $end
$scope module rc_osc $end
$var wire 1 " dvdd $end
$var wire 1 # dvss $end
$var wire 1 : osc_ena $end
$var reg 1 ' osc_ck $end
$upscope $end
$scope module rstring_mux $end
$var wire 1 ! avss $end
$var wire 1 " dvdd $end
$var wire 1 # dvss $end
$var wire 1 * ena $end
$var wire 8 W vtrip_decoded [7:0] $end
$var wire 8 X otrip_decoded [7:0] $end
$var real 1 Y avdd $end
$var real 1 Z vin_brout $end
$var real 1 [ vin_vunder $end
$var real 1 \ vtrip_7 $end
$var real 1 ] vtrip_6 $end
$var real 1 ^ vtrip_5 $end
$var real 1 _ vtrip_4 $end
$var real 1 ` vtrip_3 $end
$var real 1 a vtrip_2 $end
$var real 1 b vtrip_1 $end
$var real 1 c vtrip_0 $end
$upscope $end
$upscope $end
$scope module brownout_dig $end
$var wire 1 ) brout_filt $end
$var wire 1 d brout_filt_ena_rsb $end
$var wire 1 * ena $end
$var wire 1 + force_rc_osc $end
$var wire 1 , force_short_oneshot $end
$var wire 1 ' osc_ck $end
$var wire 1 : osc_ena $end
$var wire 3 e otrip [2:0] $end
$var wire 3 f vtrip [2:0] $end
$var wire 1 % timed_out $end
$var wire 1 8 out_unbuf $end
$var reg 1 g brout_filt_retimed $end
$var reg 12 h cnt [11:0] $end
$var reg 1 i cnt_rsb $end
$var reg 1 j cnt_rsb_stg1 $end
$var reg 1 k cnt_rsb_stg2 $end
$var reg 8 l otrip_decoded [7:0] $end
$var reg 8 m vtrip_decoded [7:0] $end
$upscope $end
$upscope $end
$upscope $end
$enddefinitions $end
$comment Show the parameter values. $end
$dumpall
$end
#0
$dumpvars
b10000000 m
b10000000 l
0k
0j
0i
b111111111111 h
0g
b111 f
b111 e
0d
r2.2 c
r2.2 b
r2.2 a
r2.2 `
r2.2 _
r2.2 ^
r2.2 ]
r2.2 \
r2.2 [
r2.2 Z
r2.2 Y
b10000000 X
b10000000 W
r0 V
r0 U
r2e-07 T
r2.2 S
r0 R
r2.2 Q
r1.2 P
r2.2 O
r0 N
r2.2 M
r1.2 L
r2.2 K
r0 J
r0 I
r2.2 H
r2.2 G
r1.2 F
r2e-07 E
r2.2 D
b10000000 C
b10000000 B
0A
r0 @
r2.2 ?
r2.2 >
r1.2 =
r2e-07 <
r2.2 ;
0:
b10000000 9
18
b10000000 7
b111 6
b111 5
r2.2 4
r2.2 3
r1.2 2
r2e-07 1
r2.2 0
b111 /
b111 .
0-
0,
0+
0*
0)
0(
0'
1&
1%
1$
0#
1"
0!
$end
#8000000
r3.3 4
r3.3 ?
r3.3 H
r3.3 M
r3.3 Z
r3.3 3
r3.3 >
r3.3 G
r3.3 Q
r3.3 [
r3.3 c
r3.3 b
r3.3 a
r3.3 `
r3.3 _
r3.3 ^
r3.3 ]
r3.3 \
r3.3 0
r3.3 ;
r3.3 D
r3.3 K
r3.3 O
r3.3 S
r3.3 Y
#16000000
r1.32 3
r1.32 >
r1.32 G
r1.32 Q
r1.32 [
r1.32 4
r1.32 ?
r1.32 H
r1.32 M
r1.32 Z
r7e-07 J
r7e-07 N
r7e-07 R
r7e-07 V
r1.65 c
r1.602857142857143 b
r1.555714285714286 a
r1.508571428571429 `
r1.461428571428572 _
r1.414285714285714 ^
r1.367142857142857 ]
r1.32 \
1*
#24000000
1:
1d
0$
1)
1A
r0.8800000000000001 4
r0.8800000000000001 ?
r0.8800000000000001 H
r0.8800000000000001 M
r0.8800000000000001 Z
r0.8800000000000001 3
r0.8800000000000001 >
r0.8800000000000001 G
r0.8800000000000001 Q
r0.8800000000000001 [
r1.1 c
r1.068571428571429 b
r1.037142857142857 a
r1.005714285714286 `
r0.9742857142857144 _
r0.9428571428571429 ^
r0.9114285714285716 ]
r0.8800000000000001 \
r2.2 0
r2.2 ;
r2.2 D
r2.2 K
r2.2 O
r2.2 S
r2.2 Y
#24011955
0&
08
1j
1g
1'
#24024150
0'
#24036345
1k
1'
#24048540
0'
#24060735
1i
1'
#24072930
0'
#24085125
0%
b0 h
1'
