verilog/brownout_dig.v
module brownout_dig(
//INPUTS
input logic [2:0] otrip,
input logic [2:0] vtrip,
input logic ena,
input logic force_ena_rc_osc,
input logic force_dis_rc_osc,
input logic force_short_oneshot,
input logic brout_filt,
input logic osc_ck,
//OUTPUTS
output osc_ena,
output out_unbuf,
output logic [7:0] otrip_decoded,
output logic [7:0] vtrip_decoded,
//DEBUG OUTPUTS
output timed_out
);

  //assign vunder = vunder_unbuf;

  //TRIP-VOLTAGE 3-to-8 DECODERS
  always @ (otrip) begin
    case(otrip)
      3'b111: otrip_decoded = 8'b10000000;
      3'b110: otrip_decoded = 8'b01000000;
      3'b101: otrip_decoded = 8'b00100000;
      3'b100: otrip_decoded = 8'b00010000;
      3'b011: otrip_decoded = 8'b00001000;
      3'b010: otrip_decoded = 8'b00000100;
      3'b001: otrip_decoded = 8'b00000010;
      3'b000: otrip_decoded = 8'b00000001;
    endcase
  end

  always @ (vtrip) begin
    case(vtrip)
      3'b111: vtrip_decoded = 8'b10000000;
      3'b110: vtrip_decoded = 8'b01000000;
      3'b101: vtrip_decoded = 8'b00100000;
      3'b100: vtrip_decoded = 8'b00010000;
      3'b011: vtrip_decoded = 8'b00001000;
      3'b010: vtrip_decoded = 8'b00000100;
      3'b001: vtrip_decoded = 8'b00000010;
      3'b000: vtrip_decoded = 8'b00000001;
    endcase
  end

  assign osc_ena = force_ena_rc_osc | (!force_dis_rc_osc & (ena & (brout_filt | !out_unbuf)));
  wire brout_filt_ena_rsb;

  //BROUT_FILT RETIME
  assign brout_filt_ena_rsb = ena & brout_filt;

  reg brout_filt_retimed;
  always @ (posedge osc_ck or negedge brout_filt_ena_rsb) begin
    if (!brout_filt_ena_rsb) begin
      brout_filt_retimed <= 0;
    end else begin
      brout_filt_retimed <= brout_filt;
    end
  end

  //COUNTER RESET
  reg cnt_rsb_stg1, cnt_rsb_stg2, cnt_rsb;

  always @ (posedge osc_ck or negedge ena) begin
    if (!ena) begin
      cnt_rsb_stg1 <= 0;
      cnt_rsb_stg2 <= 0;
      cnt_rsb <= 0;
    end else begin
      cnt_rsb_stg1 <= 1;
      cnt_rsb_stg2 <= cnt_rsb_stg1;
      cnt_rsb <= cnt_rsb_stg2;
    end
  end

  //12-BIT BROWN-OUT ONE-SHOT
  reg [11:0] cnt;

  assign timed_out = (cnt == 12'b111111111111);
  assign out_unbuf = brout_filt_retimed ? 0 : timed_out;

  always @ (posedge osc_ck or negedge cnt_rsb) begin
    if (!cnt_rsb) begin
      cnt <= 12'b111111111111;
    end else begin
      cnt <= brout_filt_retimed ? 0 : timed_out ? cnt : force_short_oneshot ? (cnt & 12'b111000000000) + 12'b001111111111 : cnt + 1;
    end
  end

endmodule

verilog/behavioral/rc_osc.v
################################################################################        
#Copyright 2024 Ajacci, Ltd. Co.
#License: Apache License, Version 2.0 with Addendum, see NOTICE
#Date: 22 March, 2024   Rev 0
#Description: RC oscillator model
################################################################################

module rc_osc(
input logic osc_ena,
input logic dvdd,
input logic dvss,
output logic osc_ck
);

always #12195.2 osc_ck = osc_ena ? ~osc_ck : 0;

initial begin
  osc_ck <= 0;
end
endmodule

verilog/behavioral/comparator.v
################################################################################        
#Copyright 2024 Ajacci, Ltd. Co.
#License: Apache License, Version 2.0 with Addendum, see NOTICE
#Date: 22 March, 2024   Rev 0
#Description: Comparator model
################################################################################

module comparator(
input real avdd,
input logic avss,
input logic dvdd,
input logic dvss,
input real vinp,
input real vinn,
input logic ena,
input real ibias,
output dout
);

assign dout = ena & (ibias > 200e-9) ? (vinp > vinn) ? 1 : 0 : 0;

endmodule

verilog/behavioral/ibias_gen.v
################################################################################        
#Copyright 2024 Ajacci, Ltd. Co.
#License: Apache License, Version 2.0 with Addendum, see NOTICE
#Date: 22 March, 2024   Rev 0
#Description: Bias generator model
################################################################################

module ibias_gen(
input real avdd,
input logic avss,
input logic dvdd,
input logic dvss,
input logic ena,
input logic isrc_sel,
input real ibg_200n,
output real ibias,
output real itest
);

assign ibias = ena ? isrc_sel ? 800e-9 : 700e-9 : 0;

endmodule

verilog/behavioral/rstring_mux.v
################################################################################        
#Copyright 2024 Ajacci, Ltd. Co.
#License: Apache License, Version 2.0 with Addendum, see NOTICE
#Date: 22 March, 2024   Rev 0
#Description: Resistor string with analog mux model
################################################################################

module rstring_mux(
//INPUT
input real avdd,
input logic avss,
input logic dvdd,
input logic dvss,
input logic ena,
input logic [7:0] otrip_decoded,
input logic [7:0] vtrip_decoded,
//OUTPUTS
output real vin_brout,
output real vin_vunder
);

`define UNIT_R 50e3

real vtrip_7;
real vtrip_6;
real vtrip_5;
real vtrip_4;
real vtrip_3;
real vtrip_2;
real vtrip_1;
real vtrip_0;

assign vtrip_0 = ena ? avdd * (`UNIT_R*7 + `UNIT_R*28) / (`UNIT_R*70) : avdd;
assign vtrip_1 = ena ? avdd * (`UNIT_R*6 + `UNIT_R*28) / (`UNIT_R*70) : avdd;
assign vtrip_2 = ena ? avdd * (`UNIT_R*5 + `UNIT_R*28) / (`UNIT_R*70) : avdd;
assign vtrip_3 = ena ? avdd * (`UNIT_R*4 + `UNIT_R*28) / (`UNIT_R*70) : avdd;
assign vtrip_4 = ena ? avdd * (`UNIT_R*3 + `UNIT_R*28) / (`UNIT_R*70) : avdd;
assign vtrip_5 = ena ? avdd * (`UNIT_R*2 + `UNIT_R*28) / (`UNIT_R*70) : avdd;
assign vtrip_6 = ena ? avdd * (`UNIT_R*1 + `UNIT_R*28) / (`UNIT_R*70) : avdd;
assign vtrip_7 = ena ? avdd * (`UNIT_R*0 + `UNIT_R*28) / (`UNIT_R*70) : avdd;

  always @ (vtrip_7, vtrip_6, vtrip_5, vtrip_4, vtrip_3, vtrip_2, vtrip_1, vtrip_0, otrip_decoded) begin
    case (otrip_decoded)
      8'b10000000: vin_brout = vtrip_7;
      8'b01000000: vin_brout = vtrip_6;
      8'b00100000: vin_brout = vtrip_5;
      8'b00010000: vin_brout = vtrip_4;
      8'b00001000: vin_brout = vtrip_3;
      8'b00000100: vin_brout = vtrip_2;
      8'b00000010: vin_brout = vtrip_1;
      8'b00000001: vin_brout = vtrip_0;
      default: vin_brout = 0;
    endcase
  end

  always @ (vtrip_7, vtrip_6, vtrip_5, vtrip_4, vtrip_3, vtrip_2, vtrip_1, vtrip_0, otrip_decoded) begin
    case (vtrip_decoded)
      8'b10000000: vin_vunder = vtrip_7;
      8'b01000000: vin_vunder = vtrip_6;
      8'b00100000: vin_vunder = vtrip_5;
      8'b00010000: vin_vunder = vtrip_4;
      8'b00001000: vin_vunder = vtrip_3;
      8'b00000100: vin_vunder = vtrip_2;
      8'b00000010: vin_vunder = vtrip_1;
      8'b00000001: vin_vunder = vtrip_0;
      default: vin_vunder = 0;
    endcase
  end

endmodule

verilog/brownout_ana.v
module brownout_ana(
//INPUTS
input real avdd,
input logic avss,
input logic dvdd,
input logic dvss,
input logic [7:0] otrip_decoded,
input logic [7:0] vtrip_decoded,
input real vbg_1v2,
input logic ena,
input logic isrc_sel,
input real ibg_200n,
input logic osc_ena,
input logic out_unbuf,
//OUTPTUS
output brout_filt,
output out,
output vunder,
output osc_ck,
output real vin_brout,
output real vin_vunder,
output real itest
);

//BUFFERS
assign vunder = ~vunder_unbuf;
assign out = out_unbuf;

rstring_mux rstring_mux(
.avdd(avdd),
.avss(avss),
.dvdd(dvdd),
.dvss(dvss),
.ena(ena),
.otrip_decoded(otrip_decoded), //lvls not modeled
.vtrip_decoded(vtrip_decoded), //lvls not modeled
.vin_brout(vin_brout),
.vin_vunder(vin_vunder)
);

real ibias;

ibias_gen ibias_gen(
.avdd(avdd),
.avss(avss),
.dvdd(dvdd),
.dvss(dvss),
.ena(ena),
.isrc_sel(isrc_sel),
.ibg_200n(ibg_200n),
.ibias(ibias),
.itest(itest)
);

comparator comparator_brout(
.avdd(avdd),
.avss(avss),
.dvdd(dvdd),
.dvss(dvss),
.vinp(vbg_1v2),
.vinn(vin_brout),
.ena(ena),
.ibias(ibias),
.dout(brout_filt)
);

comparator comparator_vunder(
.avdd(avdd),
.avss(avss),
.dvdd(dvdd),
.dvss(dvss),
.vinp(vbg_1v2),
.vinn(vin_vunder),
.ena(ena),
.ibias(ibias),
.dout(vunder_unbuf)
);

rc_osc rc_osc(
.dvdd(dvdd),
.dvss(dvss),
.osc_ena(osc_ena),
.osc_ck(osc_ck)
);

endmodule

verilog/brownout.v
`include "behavioral/rc_osc.v"
`include "behavioral/rstring_mux.v"
`include "behavioral/comparator.v"
`include "behavioral/ibias_gen.v"
`include "brownout_ana.v"
`include "brownout_dig.v"

module brownout(
//INPUTS
input real avdd,
input logic avss,
input logic dvdd,
input logic dvss,
input real vbg_1v2,
input logic [2:0] otrip,
input logic [2:0] vtrip,
input logic ena,
input logic force_ena_rc_osc,
input logic force_dis_rc_osc,
input logic force_short_oneshot,
input logic isrc_sel, //chooses between internal bias gen (0) or external bandgap current (1)
input real ibg_200n, //200nA bandgap current
//OUTPUTS
output out,
output vunder,
//DEBUG OUTPUTS
output osc_ck,
output real itest, //700nA bias current
output brout_filt,
output real vin_brout,
output real vin_vunder,
output timed_out
);

wire [7:0] otrip_decoded;
wire [7:0] vtrip_decoded;

brownout_ana brownout_ana(
//INPUTS
.avdd(avdd),
.avss(avss),
.dvdd(dvdd),
.dvss(dvss),
.otrip_decoded(otrip_decoded),
.vtrip_decoded(vtrip_decoded),
.vbg_1v2(vbg_1v2),
.ena(ena),
.isrc_sel(isrc_sel),
.ibg_200n(ibg_200n),
.osc_ena(osc_ena),
.out_unbuf(out_unbuf),
//OUTPUTS
.brout_filt(brout_filt),
.out(out),
.vunder(vunder),
.osc_ck(osc_ck),
//DEBUG OUTPUTS
.vin_brout(vin_brout), //input to comparator for comparing to 1.2V bg voltage
.vin_vunder(vin_vunder), //input to comparator for comparing to 1.2V bg voltage
.itest(itest) //mirror of current gen 0.7uA nominal
);

brownout_dig brownout_dig(
//INPUTS
.otrip(otrip),
.vtrip(vtrip),
.ena(ena),
.force_ena_rc_osc(force_ena_rc_osc),
.force_dis_rc_osc(force_dis_rc_osc),
.force_short_oneshot(force_short_oneshot),
.brout_filt(brout_filt),
//.vunder_unbuf(vunder_unbuf),
.osc_ck(osc_ck),
//OUTPUTS
.osc_ena(osc_ena),
.out_unbuf(out_unbuf),
//.vunder(vunder),
.otrip_decoded(otrip_decoded),
.vtrip_decoded(vtrip_decoded),
//DEBUG OUTPUTS
.timed_out(timed_out)
);

endmodule

verilog/tb_brownout.v
`include "brownout.v"
module tb_brownout();

real avdd;
real vbg_1v2;
logic [2:0] otrip;
logic [2:0] vtrip;
logic ena;
logic force_ena_rc_osc;
logic force_dis_rc_osc;
logic force_short_oneshot;
logic isrc_sel;
real ibg_200n;
real vin_brout;
real vin_vunder;

brownout brownout(
//INPUTS
.avdd(avdd),
.avss(avss),
.dvdd(dvdd),
.dvss(dvss),
.vbg_1v2(vbg_1v2),
.otrip(otrip),
.vtrip(vtrip),
.ena(ena), //debug
.force_ena_rc_osc(force_ena_rc_osc), //debug
.force_dis_rc_osc(force_dis_rc_osc), //debug
.force_short_oneshot(force_short_oneshot), //debug, fast sim
.isrc_sel(isrc_sel), //debug
.ibg_200n(ibg_200n), //debug 200nA current
//OUTPUTS
.out(out),
.vunder(vunder),
//DEBUG OUTPUTS
.osc_ck(osc_ck),
.itest(itest),
.brout_filt(brout_filt),
.vin_brout(vin_brout),
.vin_vunder(vin_vunder),
.timed_out(timed_out)
);

assign avss = 1'b0;
assign dvdd = 1'b1;
assign dvss = 1'b0;

initial begin
  $dumpfile("tb_brownout.vcd");
  $dumpvars(0,tb_brownout);

  //INPUTS
  avdd = 2.2;
  vbg_1v2 = 1.2;
  otrip = 3'b111;
  vtrip = 3'b111;
  //DEBUG INPUTS
  ena = 1'b0;
  force_ena_rc_osc = 1'b0;
  force_dis_rc_osc = 1'b0;
  force_short_oneshot = 1'b0;
  isrc_sel = 1'b0;
  ibg_200n = 200e-9;
  #1000
  ena = 1'b1;
  #8000000
  avdd = 3.3;
  #8000000
  ena = 1'b1;
  #8000000
  avdd = 2.2;
  #8000000
  avdd = 3.3;
  #120000000
  avdd = 2.2;
  #800000
  avdd = 3.3;
  #120000000
  $finish;
end


endmodule

verilog/tb_brownout.vcd
$date
	Wed Mar 20 20:44:58 2024
$end
$version
	Icarus Verilog
$end
$timescale
	1s
$end
$scope module tb_brownout $end
$var wire 1 ! avss $end
$var wire 1 " dvdd $end
$var wire 1 # dvss $end
$var wire 1 $ vunder $end
$var wire 1 % timed_out $end
$var wire 1 & out $end
$var wire 1 ' osc_ck $end
$var wire 1 ( itest $end
$var wire 1 ) brout_filt $end
$var reg 1 * ena $end
$var reg 1 + force_dis_rc_osc $end
$var reg 1 , force_ena_rc_osc $end
$var reg 1 - force_short_oneshot $end
$var reg 1 . isrc_sel $end
$var reg 3 / otrip [2:0] $end
$var reg 3 0 vtrip [2:0] $end
$var real 1 1 avdd $end
$var real 1 2 ibg_200n $end
$var real 1 3 vbg_1v2 $end
$var real 1 4 vin_vunder $end
$var real 1 5 vin_brout $end
$scope module brownout $end
$var wire 1 ! avss $end
$var wire 1 " dvdd $end
$var wire 1 # dvss $end
$var wire 1 * ena $end
$var wire 1 + force_dis_rc_osc $end
$var wire 1 , force_ena_rc_osc $end
$var wire 1 - force_short_oneshot $end
$var wire 1 . isrc_sel $end
$var wire 3 6 otrip [2:0] $end
$var wire 3 7 vtrip [2:0] $end
$var wire 1 $ vunder $end
$var wire 8 8 vtrip_decoded [7:0] $end
$var wire 1 % timed_out $end
$var wire 1 9 out_unbuf $end
$var wire 1 & out $end
$var wire 8 : otrip_decoded [7:0] $end
$var wire 1 ; osc_ena $end
$var wire 1 ' osc_ck $end
$var wire 1 ) brout_filt $end
$var real 1 < avdd $end
$var real 1 = ibg_200n $end
$var real 1 > vbg_1v2 $end
$var real 1 ? vin_vunder $end
$var real 1 @ vin_brout $end
$var real 1 A itest $end
$scope module brownout_ana $end
$var wire 1 ! avss $end
$var wire 1 " dvdd $end
$var wire 1 # dvss $end
$var wire 1 * ena $end
$var wire 1 . isrc_sel $end
$var wire 1 & out $end
$var wire 1 $ vunder $end
$var wire 1 B vunder_unbuf $end
$var wire 8 C vtrip_decoded [7:0] $end
$var wire 1 9 out_unbuf $end
$var wire 8 D otrip_decoded [7:0] $end
$var wire 1 ; osc_ena $end
$var wire 1 ' osc_ck $end
$var wire 1 ) brout_filt $end
$var real 1 E avdd $end
$var real 1 F ibg_200n $end
$var real 1 G vbg_1v2 $end
$var real 1 H vin_vunder $end
$var real 1 I vin_brout $end
$var real 1 J itest $end
$var real 1 K ibias $end
$scope module comparator_brout $end
$var wire 1 ! avss $end
$var wire 1 " dvdd $end
$var wire 1 # dvss $end
$var wire 1 * ena $end
$var wire 1 ) dout $end
$var real 1 L avdd $end
$var real 1 M vinp $end
$var real 1 N vinn $end
$var real 1 O ibias $end
$upscope $end
$scope module comparator_vunder $end
$var wire 1 ! avss $end
$var wire 1 " dvdd $end
$var wire 1 # dvss $end
$var wire 1 * ena $end
$var wire 1 B dout $end
$var real 1 P avdd $end
$var real 1 Q vinp $end
$var real 1 R vinn $end
$var real 1 S ibias $end
$upscope $end
$scope module ibias_gen $end
$var wire 1 ! avss $end
$var wire 1 " dvdd $end
$var wire 1 # dvss $end
$var wire 1 * ena $end
$var wire 1 . isrc_sel $end
$var real 1 T avdd $end
$var real 1 U ibg_200n $end
$var real 1 V itest $end
$var real 1 W ibias $end
$upscope $end
$scope module rc_osc $end
$var wire 1 " dvdd $end
$var wire 1 # dvss $end
$var wire 1 ; osc_ena $end
$var reg 1 ' osc_ck $end
$upscope $end
$scope module rstring_mux $end
$var wire 1 ! avss $end
$var wire 1 " dvdd $end
$var wire 1 # dvss $end
$var wire 1 * ena $end
$var wire 8 X vtrip_decoded [7:0] $end
$var wire 8 Y otrip_decoded [7:0] $end
$var real 1 Z avdd $end
$var real 1 [ vin_brout $end
$var real 1 \ vin_vunder $end
$var real 1 ] vtrip_7 $end
$var real 1 ^ vtrip_6 $end
$var real 1 _ vtrip_5 $end
$var real 1 ` vtrip_4 $end
$var real 1 a vtrip_3 $end
$var real 1 b vtrip_2 $end
$var real 1 c vtrip_1 $end
$var real 1 d vtrip_0 $end
$upscope $end
$upscope $end
$scope module brownout_dig $end
$var wire 1 ) brout_filt $end
$var wire 1 e brout_filt_ena_rsb $end
$var wire 1 * ena $end
$var wire 1 + force_dis_rc_osc $end
$var wire 1 , force_ena_rc_osc $end
$var wire 1 - force_short_oneshot $end
$var wire 1 ' osc_ck $end
$var wire 1 ; osc_ena $end
$var wire 3 f otrip [2:0] $end
$var wire 3 g vtrip [2:0] $end
$var wire 1 % timed_out $end
$var wire 1 9 out_unbuf $end
$var reg 1 h brout_filt_retimed $end
$var reg 12 i cnt [11:0] $end
$var reg 1 j cnt_rsb $end
$var reg 1 k cnt_rsb_stg1 $end
$var reg 1 l cnt_rsb_stg2 $end
$var reg 8 m otrip_decoded [7:0] $end
$var reg 8 n vtrip_decoded [7:0] $end
$upscope $end
$upscope $end
$upscope $end
$enddefinitions $end
$comment Show the parameter values. $end
$dumpall
$end
#0
$dumpvars
b10000000 n
b10000000 m
0l
0k
0j
b111111111111 i
0h
b111 g
b111 f
0e
r2.2 d
r2.2 c
r2.2 b
r2.2 a
r2.2 `
r2.2 _
r2.2 ^
r2.2 ]
r2.2 \
r2.2 [
r2.2 Z
b10000000 Y
b10000000 X
r0 W
r0 V
r2e-07 U
r2.2 T
r0 S
r2.2 R
r1.2 Q
r2.2 P
r0 O
r2.2 N
r1.2 M
r2.2 L
r0 K
r0 J
r2.2 I
r2.2 H
r1.2 G
r2e-07 F
r2.2 E
b10000000 D
b10000000 C
0B
r0 A
r2.2 @
r2.2 ?
r1.2 >
r2e-07 =
r2.2 <
0;
b10000000 :
19
b10000000 8
b111 7
b111 6
r2.2 5
r2.2 4
r1.2 3
r2e-07 2
r2.2 1
b111 0
b111 /
0.
0-
0,
0+
0*
0)
0(
0'
1&
1%
1$
0#
1"
0!
$end
#1000
1;
1e
0$
1)
1B
r0.8800000000000001 5
r0.8800000000000001 @
r0.8800000000000001 I
r0.8800000000000001 N
r0.8800000000000001 [
r0.8800000000000001 4
r0.8800000000000001 ?
r0.8800000000000001 H
r0.8800000000000001 R
r0.8800000000000001 \
r7e-07 K
r7e-07 O
r7e-07 S
r7e-07 W
r1.1 d
r1.068571428571429 c
r1.037142857142857 b
r1.005714285714286 a
r0.9742857142857144 `
r0.9428571428571429 _
r0.9114285714285716 ^
r0.8800000000000001 ]
1*
#12195
0&
09
1k
1h
1'
#24390
0'
#36585
1l
1'
#48780
0'
#60975
1j
1'
#73170
0'
#85365
0%
b0 i
1'
#97560
0'
#109755
1'
#121950
0'
#134145
1'
#146340
0'
#158535
1'
#170730
0'
#182925
1'
#195120
0'
#207315
1'
#219510
0'
#231705
1'
#243900
0'
#256095
1'
#268290
0'
#280485
1'
#292680
0'
#304875
1'
#317070
0'
#329265
1'
#341460
0'
#353655
1'
#365850
0'
#378045
1'
#390240
0'
#402435
1'
#414630
0'
#426825
1'
#439020
0'
#451215
1'
#463410
0'
#475605
1'
#487800
0'
#499995
1'
#512190
0'
#524385
1'
#536580
0'
#548775
1'
#560970
0'
#573165
1'
#585360
0'
#597555
1'
#609750
0'
#621945
1'
#634140
0'
#646335
1'
#658530
0'
#670725
1'
#682920
0'
#695115
1'
#707310
0'
#719505
1'
#731700
0'
#743895
1'
#756090
0'
#768285
1'
#780480
0'
#792675
1'
#804870
0'
#817065
1'
#829260
0'
#841455
1'
#853650
0'
#865845
1'
#878040
0'
#890235
1'
#902430
0'
#914625
1'
#926820
0'
#939015
1'
#951210
0'
#963405
1'
#975600
0'
#987795
1'
#999990
0'
#1012185
1'
#1024380
0'
#1036575
1'
#1048770
0'
#1060965
1'
#1073160
0'
#1085355
1'
#1097550
0'
#1109745
1'
#1121940
0'
#1134135
1'
#1146330
0'
#1158525
1'
#1170720
0'
#1182915
1'
#1195110
0'
#1207305
1'
#1219500
0'
#1231695
1'
#1243890
0'
#1256085
1'
#1268280
0'
#1280475
1'
#1292670
0'
#1304865
1'
#1317060
0'
#1329255
1'
#1341450
0'
#1353645
1'
#1365840
0'
#1378035
1'
#1390230
0'
#1402425
1'
#1414620
0'
#1426815
1'
#1439010
0'
#1451205
1'
#1463400
0'
#1475595
1'
#1487790
0'
#1499985
1'
#1512180
0'
#1524375
1'
#1536570
0'
#1548765
1'
#1560960
0'
#1573155
1'
#1585350
0'
#1597545
1'
#1609740
0'
#1621935
1'
#1634130
0'
#1646325
1'
#1658520
0'
#1670715
1'
#1682910
0'
#1695105
1'
#1707300
0'
#1719495
1'
#1731690
0'
#1743885
1'
#1756080
0'
#1768275
1'
#1780470
0'
#1792665
1'
#1804860
0'
#1817055
1'
#1829250
0'
#1841445
1'
#1853640
0'
#1865835
1'
#1878030
0'
#1890225
1'
#1902420
0'
#1914615
1'
#1926810
0'
#1939005
1'
#1951200
0'
#1963395
1'
#1975590
0'
#1987785
1'
#1999980
0'
#2012175
1'
#2024370
0'
#2036565
1'
#2048760
0'
#2060955
1'
#2073150
0'
#2085345
1'
#2097540
0'
#2109735
1'
#2121930
0'
#2134125
1'
#2146320
0'
#2158515
1'
#2170710
0'
#2182905
1'
#2195100
0'
#2207295
1'
#2219490
0'
#2231685
1'
#2243880
0'
#2256075
1'
#2268270
0'
#2280465
1'
#2292660
0'
#2304855
1'
#2317050
0'
#2329245
1'
#2341440
0'
#2353635
1'
#2365830
0'
#2378025
1'
#2390220
0'
#2402415
1'
#2414610
0'
#2426805
1'
#2439000
0'
#2451195
1'
#2463390
0'
#2475585
1'
#2487780
0'
#2499975
1'
#2512170
0'
#2524365
1'
#2536560
0'
#2548755
1'
#2560950
0'
#2573145
1'
#2585340
0'
#2597535
1'
#2609730
0'
#2621925
1'
#2634120
0'
#2646315
1'
#2658510
0'
#2670705
1'
#2682900
0'
#2695095
1'
#2707290
0'
#2719485
1'
#2731680
0'
#2743875
1'
#2756070
0'
#2768265
1'
#2780460
0'
#2792655
1'
#2804850
0'
#2817045
1'
#2829240
0'
#2841435
1'
#2853630
0'
#2865825
1'
#2878020
0'
#2890215
1'
#2902410
0'
#2914605
1'
#2926800
0'
#2938995
1'
#2951190
0'
#2963385
1'
#2975580
0'
#2987775
1'
#2999970
0'
#3012165
1'
#3024360
0'
#3036555
1'
#3048750
0'
#3060945
1'
#3073140
0'
#3085335
1'
#3097530
0'
#3109725
1'
#3121920
0'
#3134115
1'
#3146310
0'
#3158505
1'
#3170700
0'
#3182895
1'
#3195090
0'
#3207285
1'
#3219480
0'
#3231675
1'
#3243870
0'
#3256065
1'
#3268260
0'
#3280455
1'
#3292650
0'
#3304845
1'
#3317040
0'
#3329235
1'
#3341430
0'
#3353625
1'
#3365820
0'
#3378015
1'
#3390210
0'
#3402405
1'
#3414600
0'
#3426795
1'
#3438990
0'
#3451185
1'
#3463380
0'
#3475575
1'
#3487770
0'
#3499965
1'
#3512160
0'
#3524355
1'
#3536550
0'
#3548745
1'
#3560940
0'
#3573135
1'
#3585330
0'
#3597525
1'
#3609720
0'
#3621915
1'
#3634110
0'
#3646305
1'
#3658500
0'
#3670695
1'
#3682890
0'
#3695085
1'
#3707280
0'
#3719475
1'
#3731670
0'
#3743865
1'
#3756060
0'
#3768255
1'
#3780450
0'
#3792645
1'
#3804840
0'
#3817035
1'
#3829230
0'
#3841425
1'
#3853620
0'
#3865815
1'
#3878010
0'
#3890205
1'
#3902400
0'
#3914595
1'
#3926790
0'
#3938985
1'
#3951180
0'
#3963375
1'
#3975570
0'
#3987765
1'
#3999960
0'
#4012155
1'
#4024350
0'
#4036545
1'
#4048740
0'
#4060935
1'
#4073130
0'
#4085325
1'
#4097520
0'
#4109715
1'
#4121910
0'
#4134105
1'
#4146300
0'
#4158495
1'
#4170690
0'
#4182885
1'
#4195080
0'
#4207275
1'
#4219470
0'
#4231665
1'
#4243860
0'
#4256055
1'
#4268250
0'
#4280445
1'
#4292640
0'
#4304835
1'
#4317030
0'
#4329225
1'
#4341420
0'
#4353615
1'
#4365810
0'
#4378005
1'
#4390200
0'
#4402395
1'
#4414590
0'
#4426785
1'
#4438980
0'
#4451175
1'
#4463370
0'
#4475565
1'
#4487760
0'
#4499955
1'
#4512150
0'
#4524345
1'
#4536540
0'
#4548735
1'
#4560930
0'
#4573125
1'
#4585320
0'
#4597515
1'
#4609710
0'
#4621905
1'
#4634100
0'
#4646295
1'
#4658490
0'
#4670685
1'
#4682880
0'
#4695075
1'
#4707270
0'
#4719465
1'
#4731660
0'
#4743855
1'
#4756050
0'
#4768245
1'
#4780440
0'
#4792635
1'
#4804830
0'
#4817025
1'
#4829220
0'
#4841415
1'
#4853610
0'
#4865805
1'
#4878000
0'
#4890195
1'
#4902390
0'
#4914585
1'
#4926780
0'
#4938975
1'
#4951170
0'
#4963365
1'
#4975560
0'
#4987755
1'
#4999950
0'
#5012145
1'
#5024340
0'
#5036535
1'
#5048730
0'
#5060925
1'
#5073120
0'
#5085315
1'
#5097510
0'
#5109705
1'
#5121900
0'
#5134095
1'
#5146290
0'
#5158485
1'
#5170680
0'
#5182875
1'
#5195070
0'
#5207265
1'
#5219460
0'
#5231655
1'
#5243850
0'
#5256045
1'
#5268240
0'
#5280435
1'
#5292630
0'
#5304825
1'
#5317020
0'
#5329215
1'
#5341410
0'
#5353605
1'
#5365800
0'
#5377995
1'
#5390190
0'
#5402385
1'
#5414580
0'
#5426775
1'
#5438970
0'
#5451165
1'
#5463360
0'
#5475555
1'
#5487750
0'
#5499945
1'
#5512140
0'
#5524335
1'
#5536530
0'
#5548725
1'
#5560920
0'
#5573115
1'
#5585310
0'
#5597505
1'
#5609700
0'
#5621895
1'
#5634090
0'
#5646285
1'
#5658480
0'
#5670675
1'
#5682870
0'
#5695065
1'
#5707260
0'
#5719455
1'
#5731650
0'
#5743845
1'
#5756040
0'
#5768235
1'
#5780430
0'
#5792625
1'
#5804820
0'
#5817015
1'
#5829210
0'
#5841405
1'
#5853600
0'
#5865795
1'
#5877990
0'
#5890185
1'
#5902380
0'
#5914575
1'
#5926770
0'
#5938965
1'
#5951160
0'
#5963355
1'
#5975550
0'
#5987745
1'
#5999940
0'
#6012135
1'
#6024330
0'
#6036525
1'
#6048720
0'
#6060915
1'
#6073110
0'
#6085305
1'
#6097500
0'
#6109695
1'
#6121890
0'
#6134085
1'
#6146280
0'
#6158475
1'
#6170670
0'
#6182865
1'
#6195060
0'
#6207255
1'
#6219450
0'
#6231645
1'
#6243840
0'
#6256035
1'
#6268230
0'
#6280425
1'
#6292620
0'
#6304815
1'
#6317010
0'
#6329205
1'
#6341400
0'
#6353595
1'
#6365790
0'
#6377985
1'
#6390180
0'
#6402375
1'
#6414570
0'
#6426765
1'
#6438960
0'
#6451155
1'
#6463350
0'
#6475545
1'
#6487740
0'
#6499935
1'
#6512130
0'
#6524325
1'
#6536520
0'
#6548715
1'
#6560910
0'
#6573105
1'
#6585300
0'
#6597495
1'
#6609690
0'
#6621885
1'
#6634080
0'
#6646275
1'
#6658470
0'
#6670665
1'
#6682860
0'
#6695055
1'
#6707250
0'
#6719445
1'
#6731640
0'
#6743835
1'
#6756030
0'
#6768225
1'
#6780420
0'
#6792615
1'
#6804810
0'
#6817005
1'
#6829200
0'
#6841395
1'
#6853590
0'
#6865785
1'
#6877980
0'
#6890175
1'
#6902370
0'
#6914565
1'
#6926760
0'
#6938955
1'
#6951150
0'
#6963345
1'
#6975540
0'
#6987735
1'
#6999930
0'
#7012125
1'
#7024320
0'
#7036515
1'
#7048710
0'
#7060905
1'
#7073100
0'
#7085295
1'
#7097490
0'
#7109685
1'
#7121880
0'
#7134075
1'
#7146270
0'
#7158465
1'
#7170660
0'
#7182855
1'
#7195050
0'
#7207245
1'
#7219440
0'
#7231635
1'
#7243830
0'
#7256025
1'
#7268220
0'
#7280415
1'
#7292610
0'
#7304805
1'
#7317000
0'
#7329195
1'
#7341390
0'
#7353585
1'
#7365780
0'
#7377975
1'
#7390170
0'
#7402365
1'
#7414560
0'
#7426755
1'
#7438950
0'
#7451145
1'
#7463340
0'
#7475535
1'
#7487730
0'
#7499925
1'
#7512120
0'
#7524315
1'
#7536510
0'
#7548705
1'
#7560900
0'
#7573095
1'
#7585290
0'
#7597485
1'
#7609680
0'
#7621875
1'
#7634070
0'
#7646265
1'
#7658460
0'
#7670655
1'
#7682850
0'
#7695045
1'
#7707240
0'
#7719435
1'
#7731630
0'
#7743825
1'
#7756020
0'
#7768215
1'
#7780410
0'
#7792605
1'
#7804800
0'
#7816995
1'
#7829190
0'
#7841385
1'
#7853580
0'
#7865775
1'
#7877970
0'
#7890165
1'
#7902360
0'
#7914555
1'
#7926750
0'
#7938945
1'
#7951140
0'
#7963335
1'
#7975530
0'
#7987725
1'
#7999920
0'
#8001000
0h
1$
0e
0B
0)
r1.32 4
r1.32 ?
r1.32 H
r1.32 R
r1.32 \
r1.32 5
r1.32 @
r1.32 I
r1.32 N
r1.32 [
r1.65 d
r1.602857142857143 c
r1.555714285714286 b
r1.508571428571429 a
r1.461428571428572 `
r1.414285714285714 _
r1.367142857142857 ^
r1.32 ]
r3.3 1
r3.3 <
r3.3 E
r3.3 L
r3.3 P
r3.3 T
r3.3 Z
#8012115
b1 i
1'
#8024310
0'
#8036505
b10 i
1'
#8048700
0'
#8060895
b11 i
1'
#8073090
0'
#8085285
b100 i
1'
#8097480
0'
#8109675
b101 i
1'
#8121870
0'
#8134065
b110 i
1'
#8146260
0'
#8158455
b111 i
1'
#8170650
0'
#8182845
b1000 i
1'
#8195040
0'
#8207235
b1001 i
1'
#8219430
0'
#8231625
b1010 i
1'
#8243820
0'
